more_pathlib/__init__.py
more_pathlib/common.py
more_pathlib/copy.py
more_pathlib/json.py
more_pathlib/pickle.py
more_pathlib/py.typed
more_pathlib/rm.py
more_pathlib/validation.py
more_pathlib-0.2.0.dist-info/LICENSE
more_pathlib-0.2.0.dist-info/WHEEL
more_pathlib-0.2.0.dist-info/METADATA
more_pathlib-0.2.0.dist-info/RECORD
